[
null,
{"id":1,"animationId":6,"description":"","etypeId":1,"traits":[{"code":31,"dataId":1,"value":0},{"code":22,"dataId":0,"value":0},{"code":33,"dataId":0,"value":120}],"iconIndex":97,"name":"Меч","note":"","params":[0,0,10,0,0,0,0,0],"price":500,"wtypeId":2},
{"id":2,"animationId":11,"description":"","etypeId":1,"traits":[{"code":31,"dataId":1,"value":0},{"code":22,"dataId":0,"value":0},{"code":33,"dataId":0,"value":200}],"iconIndex":102,"name":"Лук","note":"<ABS:1>\n<ammo:2>\n<range:6>\n<img:arrow>\n<vSpeed:6> //Faster\n<startSound:Crossbow>","params":[0,0,10,0,0,0,0,0],"price":500,"wtypeId":7},
{"id":3,"animationId":1,"description":"","etypeId":1,"traits":[{"code":31,"dataId":1,"value":0},{"code":22,"dataId":0,"value":0},{"code":33,"dataId":0,"value":120}],"iconIndex":101,"name":"Посох","note":"","params":[0,0,10,0,0,0,0,0],"price":400,"wtypeId":6}
]